inspeakbot/__init__.py
inspeakbot-0.1.2.dist-info/licenses/LICENSE
inspeakbot-0.1.2.dist-info/METADATA
inspeakbot-0.1.2.dist-info/WHEEL
inspeakbot-0.1.2.dist-info/top_level.txt
inspeakbot-0.1.2.dist-info/RECORD
