Metadata-Version: 2.4
Name: inspeakbot
Version: 0.1.2
Summary: Official Python SDK for InSpeak Bot API .
Home-page: https://inspeak.levelupstudios.xyz
Author: Karim Mohamed
Author-email: KimoDeveloper@levelupstudios.xyz
License: MIT
Classifier: Programming Language :: Python :: 3
Classifier: License :: OSI Approved :: MIT License
Classifier: Operating System :: OS Independent
Requires-Python: >=3.6
License-File: LICENSE
Requires-Dist: requests
Dynamic: author
Dynamic: author-email
Dynamic: classifier
Dynamic: description
Dynamic: description-content-type
Dynamic: home-page
Dynamic: license
Dynamic: license-file
Dynamic: requires-dist
Dynamic: requires-python
Dynamic: summary
